[
  {
    "year": 2012,
    "flyTo": "ATL",
    "flyFrom": "ILM",
    "num_flights": 111,
    "source": [-77.9028888889, 34.2711388889],
    "dest": [-84.427864, 33.6366996111]
  },
  {
    "year": 2013,
    "flyTo": "ATL",
    "flyFrom": "ILM",
    "num_flights": 335,
    "source": [-77.9028888889, 34.2711388889],
    "dest": [-84.427864, 33.6366996111]
  },
  {
    "year": 2014,
    "flyTo": "ATL",
    "flyFrom": "ILM",
    "num_flights": 393,
    "source": [-77.9028888889, 34.2711388889],
    "dest": [-84.427864, 33.6366996111]
  },
  {
    "year": 2015,
    "flyTo": "ATL",
    "flyFrom": "ILM",
    "num_flights": 379,
    "source": [-77.9028888889, 34.2711388889],
    "dest": [-84.427864, 33.6366996111]
  },
  {
    "year": 2016,
    "flyTo": "ATL",
    "flyFrom": "ILM",
    "num_flights": 437,
    "source": [-77.9028888889, 34.2711388889],
    "dest": [-84.427864, 33.6366996111]
  },
  {
    "year": 2017,
    "flyTo": "ATL",
    "flyFrom": "ILM",
    "num_flights": 356,
    "source": [-77.9028888889, 34.2711388889],
    "dest": [-84.427864, 33.6366996111]
  },
  {
    "year": 2018,
    "flyTo": "ATL",
    "flyFrom": "ILM",
    "num_flights": 347,
    "source": [-77.9028888889, 34.2711388889],
    "dest": [-84.427864, 33.6366996111]
  },
  {
    "year": 2019,
    "flyTo": "ATL",
    "flyFrom": "ILM",
    "num_flights": 364,
    "source": [-77.9028888889, 34.2711388889],
    "dest": [-84.427864, 33.6366996111]
  },
  {
    "year": 2020,
    "flyTo": "ATL",
    "flyFrom": "ILM",
    "num_flights": 92,
    "source": [-77.9028888889, 34.2711388889],
    "dest": [-84.427864, 33.6366996111]
  },
  {
    "year": 2021,
    "flyTo": "ATL",
    "flyFrom": "ILM",
    "num_flights": 237,
    "source": [-77.9028888889, 34.2711388889],
    "dest": [-84.427864, 33.6366996111]
  },
  {
    "year": 2022,
    "flyTo": "ATL",
    "flyFrom": "ILM",
    "num_flights": 459,
    "source": [-77.9028888889, 34.2711388889],
    "dest": [-84.427864, 33.6366996111]
  },
  {
    "year": 2023,
    "flyTo": "ATL",
    "flyFrom": "ILM",
    "num_flights": 546,
    "source": [-77.9028888889, 34.2711388889],
    "dest": [-84.427864, 33.6366996111]
  }
]
